shmview/__init__.py
shmview/shmimview.ui
shmview/shmview.py
shmview-0.0.10.dist-info/METADATA
shmview-0.0.10.dist-info/WHEEL
shmview-0.0.10.dist-info/entry_points.txt
shmview-0.0.10.dist-info/licenses/LICENSE.txt
shmview-0.0.10.dist-info/RECORD
